spyicydev_hashmap/__init__.py
spyicydev_hashmap-0.2.2.dist-info/METADATA
spyicydev_hashmap-0.2.2.dist-info/WHEEL
spyicydev_hashmap-0.2.2.dist-info/RECORD
