Metadata-Version: 2.1
Name: spyicydev-hashmap
Version: 0.2.2
Summary: 
Author: Mack Haymond
Author-email: mack.haymond@icloud.com
Requires-Python: >=3.11,<4.0
Classifier: Programming Language :: Python :: 3
Classifier: Programming Language :: Python :: 3.11
Requires-Dist: multimethod (>=1.10,<2.0)
